CHANGES.txt
README.txt
bootstrap.py
buildout.cfg
setup.py
src/z3c/__init__.py
src/z3c.blobfile.egg-info/PKG-INFO
src/z3c.blobfile.egg-info/SOURCES.txt
src/z3c.blobfile.egg-info/dependency_links.txt
src/z3c.blobfile.egg-info/namespace_packages.txt
src/z3c.blobfile.egg-info/not-zip-safe
src/z3c.blobfile.egg-info/requires.txt
src/z3c.blobfile.egg-info/top_level.txt
src/z3c/blobfile/__init__.py
src/z3c/blobfile/blobfile.txt
src/z3c/blobfile/configure.zcml
src/z3c/blobfile/copy.py
src/z3c/blobfile/file.py
src/z3c/blobfile/ftesting.zcml
src/z3c/blobfile/ftests.py
src/z3c/blobfile/i18n.py
src/z3c/blobfile/image.py
src/z3c/blobfile/interfaces.py
src/z3c/blobfile/overrides.zcml
src/z3c/blobfile/storages.py
src/z3c/blobfile/testing.py
src/z3c/blobfile/tests.py
src/z3c/blobfile/browser/__init__.py
src/z3c/blobfile/browser/configure.zcml
src/z3c/blobfile/browser/file.py
src/z3c/blobfile/browser/file_add.pt
src/z3c/blobfile/browser/file_icon.gif
src/z3c/blobfile/browser/file_upload.pt
src/z3c/blobfile/browser/image.py
src/z3c/blobfile/browser/image_edit.pt
src/z3c/blobfile/browser/image_icon.gif
src/z3c/blobfile/browser/preview.pt
src/z3c/blobfile/generations/__init__.py
src/z3c/blobfile/generations/evolve1.py
src/z3c/blobfile/generations/install.py