Metadata-Version: 1.0
Name: z3c.blobfile
Version: 0.1.4
Summary: File and Image Using Blob Support of ZODB -- Zope 3 Content Components
Home-page: http://pypi.python.org/pypi/z3c.blobfile
Author: Zope Community
Author-email: zope-dev@zope.org
License: ZPL 2.1
Keywords: zope3 ZODB blob file image content
Platform: UNKNOWN
Classifier: Development Status :: 4 - Beta
Classifier: Environment :: Web Environment
Classifier: Intended Audience :: Developers
Classifier: License :: OSI Approved :: Zope Public License
Classifier: Programming Language :: Python
Classifier: Natural Language :: English
Classifier: Operating System :: OS Independent
Classifier: Topic :: Internet :: WWW/HTTP
Classifier: Framework :: Zope3
